sip_parser/__init__.py
sip_parser/__main__.py
sip_parser/exceptions.py
sip_parser/log.conf
sip_parser/parser.py
sip_parser/sip.peg
sip_parser/visitor.py
sip_parser-0.2.1.dist-info/LICENSE
sip_parser-0.2.1.dist-info/METADATA
sip_parser-0.2.1.dist-info/WHEEL
sip_parser-0.2.1.dist-info/entry_points.txt
sip_parser-0.2.1.dist-info/top_level.txt
sip_parser-0.2.1.dist-info/RECORD
