Metadata-Version: 2.2
Name: sip-parser
Version: 0.2.1
Summary: Scenario Instance Parser
Author-email: Leon Starr <leon_starr@modelint.com>
License: MIT License
Project-URL: repository, https://github.com/modelint/sip-parser
Project-URL: documentation, https://github.com/modelint/sip-parser/wiki
Keywords: scenario population,initial instances,parser,executable uml,class model,mbse,xuml,xtuml,platform independent,sysml,leon starr,blueprint,model integration,shlaer-mellor
Classifier: License :: OSI Approved :: MIT License
Classifier: Programming Language :: Python
Classifier: Programming Language :: Python :: 3
Requires-Python: >=3.11
License-File: LICENSE
Requires-Dist: Arpeggio<3.0.0
Requires-Dist: tomli; python_version < "3.13"
Provides-Extra: build
Requires-Dist: build; extra == "build"
Requires-Dist: twine; extra == "build"
Provides-Extra: dev
Requires-Dist: bump2version; extra == "dev"
Requires-Dist: pytest; extra == "dev"
